<?xml version="1.0" encoding="UTF-8"?>
<ehcache xmlns:xsi="http://www.w3.org/2001/XMLSchema-instance"
         xsi:noNamespaceSchemaLocation="ehcache.xsd"
         updateCheck="true" monitoring="autodetect" dynamicConfig="true">
    <defaultCache maxEntriesLocalHeap="10000" eternal="false"
                  timeToIdleSeconds="300" timeToLiveSeconds="600" diskSpoolBufferSizeMB="30"
                  maxEntriesLocalDisk="10000" diskExpiryThreadIntervalSeconds="120"
                  memoryStoreEvictionPolicy="LRU" statistics="true">
        <persistence strategy="localTempSwap" />
    </defaultCache>
    <cache name="messagecache"
           maxEntriesLocalHeap="8000"
           maxEntriesLocalDisk="2000"
           eternal="false"
           diskSpoolBufferSizeMB="30"
           timeToIdleSeconds="300"
           timeToLiveSeconds="600"
           memoryStoreEvictionPolicy="LFU"
           transactionalMode="off">
        <persistence strategy="localTempSwap"/>
    </cache>
    <cache name="membercache"
           maxEntriesLocalHeap="500"
           maxEntriesLocalDisk="100"
           eternal="false"
           diskSpoolBufferSizeMB="10"
           timeToIdleSeconds="600"
           timeToLiveSeconds="800"
           memoryStoreEvictionPolicy="LFU"
           transactionalMode="off">
        <persistence strategy="localTempSwap"/>
    </cache>
</ehcache>